cmake_win_x64/__init__.py
cmake_win_x64/data/bin/cmake-gui.exe
cmake_win_x64/data/bin/cpack.exe
cmake_win_x64/data/bin/ctest.exe
cmake_win_x64/data/man/man1/ccmake.1
cmake_win_x64/data/man/man1/cmake-gui.1
cmake_win_x64/data/man/man1/cmake.1
cmake_win_x64/data/man/man1/cpack.1
cmake_win_x64/data/man/man1/ctest.1
cmake_win_x64/data/man/man7/cmake-buildsystem.7
cmake_win_x64/data/man/man7/cmake-commands.7
cmake_win_x64/data/man/man7/cmake-compile-features.7
cmake_win_x64/data/man/man7/cmake-configure-log.7
cmake_win_x64/data/man/man7/cmake-cxxmodules.7
cmake_win_x64/data/man/man7/cmake-developer.7
cmake_win_x64/data/man/man7/cmake-env-variables.7
cmake_win_x64/data/man/man7/cmake-file-api.7
cmake_win_x64/data/man/man7/cmake-generator-expressions.7
cmake_win_x64/data/man/man7/cmake-generators.7
cmake_win_x64/data/man/man7/cmake-instrumentation.7
cmake_win_x64/data/man/man7/cmake-language.7
cmake_win_x64/data/man/man7/cmake-modules.7
cmake_win_x64/data/man/man7/cmake-packages.7
cmake_win_x64/data/man/man7/cmake-policies.7
cmake_win_x64/data/man/man7/cmake-presets.7
cmake_win_x64/data/man/man7/cmake-properties.7
cmake_win_x64/data/man/man7/cmake-qt.7
cmake_win_x64/data/man/man7/cmake-server.7
cmake_win_x64/data/man/man7/cmake-toolchains.7
cmake_win_x64/data/man/man7/cmake-variables.7
cmake_win_x64/data/man/man7/cpack-generators.7
cmake_win_x64-4.1.0.post2.dist-info/METADATA
cmake_win_x64-4.1.0.post2.dist-info/WHEEL
cmake_win_x64-4.1.0.post2.dist-info/top_level.txt
cmake_win_x64-4.1.0.post2.dist-info/RECORD
