Metadata-Version: 2.4
Name: cmake_win_x64
Version: 4.1.0.post2
Summary: Segment cmake-windows-x86_64 part p2
License-Expression: MIT
